worldpoppy/__init__.py
worldpoppy/borders.py
worldpoppy/config.py
worldpoppy/download.py
worldpoppy/func_utils.py
worldpoppy/manifest_builder.py
worldpoppy/manifest_loader.py
worldpoppy/manifest_utils.py
worldpoppy/plot_utils.py
worldpoppy/raster.py
worldpoppy/tracking.py
worldpoppy/assets/global_nb_db.json
worldpoppy/assets/level0_500m_2000_2020_simplified_world.feather
worldpoppy/assets/product_definitions.toml
worldpoppy/assets/raw_api_manifest.feather
worldpoppy/assets/raw_api_manifest_timestamp.txt
worldpoppy/assets/southern_kamchatka.feather
worldpoppy-0.4.1.dist-info/licenses/LICENSE.txt
worldpoppy-0.4.1.dist-info/METADATA
worldpoppy-0.4.1.dist-info/WHEEL
worldpoppy-0.4.1.dist-info/top_level.txt
worldpoppy-0.4.1.dist-info/RECORD
