Metadata-Version: 2.4
Name: WorldPopPy
Version: 0.4.1
Summary: Python client to help you work with WorldPop data for any region on earth
Author-email: "S. Langenbach" <lungoruscello@gmail.com>
License-Expression: MPL-2.0
Project-URL: Source, https://github.com/lungoruscello/worldpoppy
Project-URL: Documentation, https://worldpoppy.readthedocs.io/en/stable/
Project-URL: Examples, https://github.com/lungoruscello/worldpoppy/tree/master/examples
Classifier: Programming Language :: Python :: 3
Classifier: Operating System :: OS Independent
Requires-Python: >=3.10
License-File: LICENSE.txt
Requires-Dist: numpy
Requires-Dist: matplotlib
Requires-Dist: httpx
Requires-Dist: click>=8.0
Requires-Dist: tabulate
Requires-Dist: platformdirs
Requires-Dist: nest_asyncio<2
Requires-Dist: pqdm>=0.2
Requires-Dist: tqdm
Requires-Dist: backoff<3,>=2
Requires-Dist: pandas
Requires-Dist: pyarrow
Requires-Dist: rioxarray
Requires-Dist: xarray
Requires-Dist: dask
Requires-Dist: bottleneck
Requires-Dist: geopandas<2
Requires-Dist: geopy
Requires-Dist: pyproj
Requires-Dist: shapely
Provides-Extra: dev
Requires-Dist: pytest>=7.0; extra == "dev"
Requires-Dist: black; extra == "dev"
Provides-Extra: build
Requires-Dist: twine>=4.0.2; extra == "build"
Requires-Dist: build; extra == "build"
Requires-Dist: wheel; extra == "build"
Provides-Extra: gdal
Requires-Dist: gdal>=3; extra == "gdal"
Provides-Extra: docs
Requires-Dist: sphinx; extra == "docs"
Requires-Dist: sphinx-rtd-theme; extra == "docs"
Requires-Dist: sphinx-autodoc-typehints; extra == "docs"
Requires-Dist: sphinxcontrib-napoleon; extra == "docs"
Requires-Dist: myst-parser; extra == "docs"
Dynamic: license-file
